skgbm/__init__.py
skgbm/base.py
skgbm/tools.py
skgbm/tree.py
skgbm/trees_extraction.py
skgbm/utils.py
skgbm/preprocessing/__init__.py
skgbm/preprocessing/discretizer.py
skgbm/preprocessing/featurizer.py
skgbm/viz/__init__.py
skgbm/viz/axil.py
skgbm/wrappers/__init__.py
skgbm/wrappers/base_wrapper.py
skgbm/wrappers/catboost_wrapper.py
skgbm/wrappers/lightgbm_wrapper.py
skgbm/wrappers/sklearn_wrapper.py
skgbm/wrappers/xgboost_wrapper.py
skgbm/xai/__init__.py
skgbm/xai/axil.py
scikit_gbm-0.2.1.dist-info/LICENSE
scikit_gbm-0.2.1.dist-info/METADATA
scikit_gbm-0.2.1.dist-info/WHEEL
scikit_gbm-0.2.1.dist-info/top_level.txt
scikit_gbm-0.2.1.dist-info/RECORD
