Metadata-Version: 2.1
Name: scikit-gbm
Version: 0.2.1
Summary: scikit-learn compatible tools to work with GBM models
Author-email: Krzysztof Joachimiak <joachimiak.krzysztof@gmail.com>
Project-URL: Homepage, https://github.com/krzjoa/scikit-gbm
Project-URL: Bug Tracker, https://github.com/krzjoa/scikit-gbm/issues
Classifier: Programming Language :: Python :: 3
Classifier: License :: OSI Approved :: MIT License
Classifier: Operating System :: OS Independent
Requires-Python: >=3.7
License-File: LICENSE
Requires-Dist: scipy >=1.9.0
Requires-Dist: numpy >=1.22.4
Requires-Dist: pandas >=1.3.5
Requires-Dist: pytest >=7.1.2
Requires-Dist: scikit-learn >=1.1.0
Requires-Dist: feature-engine >=1.4.1
Requires-Dist: numba
